{
  "html": "<table class=\"infobox vevent\"><tbody><tr><th colspan=\"2\" class=\"infobox-above summary\" style=\"font-style: italic; background: #ededed;\">La traviata</th></tr><tr><td colspan=\"2\" class=\"infobox-subheader\" style=\"font-weight: bold;\"><a href=\"/wiki/Opera\" title=\"Opera\">Opera</a> by <a href=\"/wiki/Giuseppe_Verdi\" title=\"Giuseppe Verdi\">Giuseppe Verdi</a></td></tr><tr><td colspan=\"2\" class=\"infobox-image\"><a href=\"/wiki/File:La_Traviata_Premiere_Violetta_Costume.jpg\" class=\"image\"><img alt=\"La Traviata Premiere Violetta Costume.jpg\" src=\"//upload.wikimedia.org/wikipedia/commons/f/f6/La_Traviata_Premiere_Violetta_Costume.jpg\" decoding=\"async\" width=\"176\" height=\"207\" data-file-width=\"176\" data-file-height=\"207\"></a><div class=\"infobox-caption\">Violetta's costume, premiere 1853</div></td></tr><tr><th scope=\"row\" class=\"infobox-label\">Librettist</th><td class=\"infobox-data\"><a href=\"/wiki/Francesco_Maria_Piave\" title=\"Francesco Maria Piave\">Francesco Maria Piave</a></td></tr><tr><th scope=\"row\" class=\"infobox-label\">Language</th><td class=\"infobox-data\">Italian</td></tr><tr><th scope=\"row\" class=\"infobox-label\">Based on</th><td class=\"infobox-data\"><i><a href=\"/wiki/La_Dame_aux_cam%C3%A9lias\" class=\"mw-redirect\" title=\"La Dame aux camélias\">La Dame aux camélias</a></i><br>by <a href=\"/wiki/Alexandre_Dumas_fils\" title=\"Alexandre Dumas fils\">Alexandre Dumas <i>fils</i></a></td></tr><tr><th scope=\"row\" class=\"infobox-label\">Premiere</th><td class=\"infobox-data\"><div style=\"display:inline;\" class=\"vevent\">6&nbsp;March&nbsp;1853<span style=\"display:none\">&nbsp;(<span class=\"bday dtstart published updated\">1853-03-06</span>)</span><br><div style=\"display:inline;\" class=\"summary\"><span class=\"nowrap\"><a href=\"/wiki/Teatro_La_Fenice\" class=\"mw-redirect\" title=\"Teatro La Fenice\">Teatro La Fenice</a>, Venice</span></div></div></td></tr></tbody></table>",
  "titles": [
    "La traviata"
  ],
  "Librettist": "Francesco Maria Piave",
  "Language": "Italian",
  "Based on": "La Dame aux camélias\nby Alexandre Dumas fils",
  "Premiere": "6 March 1853\nTeatro La Fenice, Venice"
}