{
  "html": "<table class=\"infobox vevent\"><tbody><tr><th colspan=\"2\" class=\"infobox-above summary\" style=\"font-style: italic; background: #ededed;\">Elektra</th></tr><tr><td colspan=\"2\" class=\"infobox-subheader\" style=\"font-weight: bold;\"><a href=\"/wiki/Opera\" title=\"Opera\">Opera</a> by <a href=\"/wiki/Richard_Strauss\" title=\"Richard Strauss\">Richard Strauss</a></td></tr><tr><td colspan=\"2\" class=\"infobox-image\"><a href=\"/wiki/File:Richard_Strauss_-_Elektra_-_titlepage_of_the_libretto_-_drawing_by_Lovis_Corinth_-_1909.png\" class=\"image\"><img alt=\"Richard Strauss - Elektra - titlepage of the libretto - drawing by Lovis Corinth - 1909.png\" src=\"//upload.wikimedia.org/wikipedia/commons/thumb/5/51/Richard_Strauss_-_Elektra_-_titlepage_of_the_libretto_-_drawing_by_Lovis_Corinth_-_1909.png/260px-Richard_Strauss_-_Elektra_-_titlepage_of_the_libretto_-_drawing_by_Lovis_Corinth_-_1909.png\" decoding=\"async\" width=\"260\" height=\"376\" srcset=\"//upload.wikimedia.org/wikipedia/commons/thumb/5/51/Richard_Strauss_-_Elektra_-_titlepage_of_the_libretto_-_drawing_by_Lovis_Corinth_-_1909.png/390px-Richard_Strauss_-_Elektra_-_titlepage_of_the_libretto_-_drawing_by_Lovis_Corinth_-_1909.png 1.5x, //upload.wikimedia.org/wikipedia/commons/thumb/5/51/Richard_Strauss_-_Elektra_-_titlepage_of_the_libretto_-_drawing_by_Lovis_Corinth_-_1909.png/520px-Richard_Strauss_-_Elektra_-_titlepage_of_the_libretto_-_drawing_by_Lovis_Corinth_-_1909.png 2x\" data-file-width=\"2140\" data-file-height=\"3096\"></a><div class=\"infobox-caption\">Cover of the libretto, drawing by <a href=\"/wiki/Lovis_Corinth\" title=\"Lovis Corinth\">Lovis Corinth</a>, 1909</div></td></tr><tr><th scope=\"row\" class=\"infobox-label\">Librettist</th><td class=\"infobox-data\"><a href=\"/wiki/Hugo_von_Hofmannsthal\" title=\"Hugo von Hofmannsthal\">Hugo von Hofmannsthal</a></td></tr><tr><th scope=\"row\" class=\"infobox-label\">Language</th><td class=\"infobox-data\">German</td></tr><tr><th scope=\"row\" class=\"infobox-label\">Based on</th><td class=\"infobox-data\"><a href=\"/wiki/Sophocles\" title=\"Sophocles\">Sophocles</a>' <i><a href=\"/wiki/Electra_(Sophocles_play)\" title=\"Electra (Sophocles play)\">Electra</a></i></td></tr><tr><th scope=\"row\" class=\"infobox-label\">Premiere</th><td class=\"infobox-data\"><div style=\"display:inline;\" class=\"vevent\">25&nbsp;January&nbsp;1909<span style=\"display:none\">&nbsp;(<span class=\"bday dtstart published updated\">1909-01-25</span>)</span><br><div style=\"display:inline;\" class=\"summary\"><a href=\"/wiki/Semperoper\" title=\"Semperoper\">Königliches Opernhaus</a>, Dresden</div></div></td></tr></tbody></table>",
  "titles": [
    "Elektra"
  ],
  "Librettist": "Hugo von Hofmannsthal",
  "Language": "German",
  "Based on": "Sophocles' Electra",
  "Premiere": "25 January 1909\nKönigliches Opernhaus, Dresden"
}