{
  "html": "<table class=\"infobox vevent\"><tbody><tr><th colspan=\"2\" class=\"infobox-above summary\" style=\"font-style: italic; background: #ededed;\">Palestrina</th></tr><tr><td colspan=\"2\" class=\"infobox-subheader\" style=\"font-weight: bold;\"><i>Musikalische Legende</i> (<a href=\"/wiki/Opera\" title=\"Opera\">Opera</a>) by <a href=\"/wiki/Hans_Pfitzner\" title=\"Hans Pfitzner\">Hans Pfitzner</a></td></tr><tr><td colspan=\"2\" class=\"infobox-image\"><a href=\"/wiki/File:Hans_Pfitzner_by_Wanda_von_Debschitz-Kunowski,_ca_1910.jpg\" class=\"image\"><img alt=\"Hans Pfitzner by Wanda von Debschitz-Kunowski, ca 1910.jpg\" src=\"//upload.wikimedia.org/wikipedia/commons/thumb/d/d1/Hans_Pfitzner_by_Wanda_von_Debschitz-Kunowski%2C_ca_1910.jpg/220px-Hans_Pfitzner_by_Wanda_von_Debschitz-Kunowski%2C_ca_1910.jpg\" decoding=\"async\" width=\"220\" height=\"281\" srcset=\"//upload.wikimedia.org/wikipedia/commons/thumb/d/d1/Hans_Pfitzner_by_Wanda_von_Debschitz-Kunowski%2C_ca_1910.jpg/330px-Hans_Pfitzner_by_Wanda_von_Debschitz-Kunowski%2C_ca_1910.jpg 1.5x, //upload.wikimedia.org/wikipedia/commons/thumb/d/d1/Hans_Pfitzner_by_Wanda_von_Debschitz-Kunowski%2C_ca_1910.jpg/440px-Hans_Pfitzner_by_Wanda_von_Debschitz-Kunowski%2C_ca_1910.jpg 2x\" data-file-width=\"599\" data-file-height=\"765\"></a><div class=\"infobox-caption\">Pfitzner, by <a href=\"/wiki/Wanda_von_Debschitz-Kunowski\" title=\"Wanda von Debschitz-Kunowski\">Wanda von Debschitz-Kunowski</a>, ca 1910</div></td></tr><tr><th scope=\"row\" class=\"infobox-label\">Librettist</th><td class=\"infobox-data\">Hans Pfitzner</td></tr><tr><th scope=\"row\" class=\"infobox-label\">Language</th><td class=\"infobox-data\">German</td></tr><tr><th scope=\"row\" class=\"infobox-label\">Premiere</th><td class=\"infobox-data\"><div style=\"display:inline;\" class=\"vevent\">12&nbsp;June&nbsp;1917<span style=\"display:none\">&nbsp;(<span class=\"bday dtstart published updated\">1917-06-12</span>)</span><br><div style=\"display:inline;\" class=\"summary\"><a href=\"/wiki/Prinzregententheater\" title=\"Prinzregententheater\">Prinzregententheater</a>, Munich</div></div></td></tr></tbody></table>",
  "titles": [
    "Palestrina"
  ],
  "Librettist": "Hans Pfitzner",
  "Language": "German",
  "Premiere": "12 June 1917\nPrinzregententheater, Munich"
}