{
  "html": "<table class=\"infobox vevent\"><tbody><tr><th colspan=\"2\" class=\"infobox-above summary\" style=\"font-style: italic; background: #ededed;\"><span title=\"German-language text\"><i lang=\"de\">Mathis der Maler</i></span></th></tr><tr><td colspan=\"2\" class=\"infobox-subheader\" style=\"font-weight: bold;\"><a href=\"/wiki/Opera\" title=\"Opera\">Opera</a> by <a href=\"/wiki/Paul_Hindemith\" title=\"Paul Hindemith\">Paul Hindemith</a></td></tr><tr><td colspan=\"2\" class=\"infobox-image\"><a href=\"/wiki/File:Grunewald_Self_Portrait.jpg\" class=\"image\"><img alt=\"Grunewald Self Portrait.jpg\" src=\"//upload.wikimedia.org/wikipedia/commons/thumb/6/61/Grunewald_Self_Portrait.jpg/220px-Grunewald_Self_Portrait.jpg\" decoding=\"async\" width=\"220\" height=\"301\" srcset=\"//upload.wikimedia.org/wikipedia/commons/thumb/6/61/Grunewald_Self_Portrait.jpg/330px-Grunewald_Self_Portrait.jpg 1.5x, //upload.wikimedia.org/wikipedia/commons/thumb/6/61/Grunewald_Self_Portrait.jpg/440px-Grunewald_Self_Portrait.jpg 2x\" data-file-width=\"727\" data-file-height=\"995\"></a><div class=\"infobox-caption\"><i><a href=\"/wiki/John_the_Evangelist\" title=\"John the Evangelist\">John the Evangelist</a></i> by <a href=\"/wiki/Matthias_Gr%C3%BCnewald\" title=\"Matthias Grünewald\">Matthias Grünewald</a>, regarded in Hindemith's time as a self-portrait</div></td></tr><tr><th scope=\"row\" class=\"infobox-label\">Translation</th><td class=\"infobox-data\"><i>Matthias the Painter</i></td></tr><tr><th scope=\"row\" class=\"infobox-label\">Librettist</th><td class=\"infobox-data\">Hindemith</td></tr><tr><th scope=\"row\" class=\"infobox-label\">Language</th><td class=\"infobox-data\">German</td></tr><tr><th scope=\"row\" class=\"infobox-label\">Based on</th><td class=\"infobox-data\"><a href=\"/wiki/Matthias_Gr%C3%BCnewald\" title=\"Matthias Grünewald\">Matthias Grünewald</a></td></tr><tr><th scope=\"row\" class=\"infobox-label\">Premiere</th><td class=\"infobox-data\"><div style=\"display:inline;\" class=\"vevent\">28&nbsp;May&nbsp;1938<span style=\"display:none\">&nbsp;(<span class=\"bday dtstart published updated\">1938-05-28</span>)</span><br><div style=\"display:inline;\" class=\"summary\"><a href=\"/wiki/Zurich_Opera\" class=\"mw-redirect\" title=\"Zurich Opera\">Zurich Opera</a></div></div></td></tr></tbody></table>",
  "titles": [
    "Mathis der Maler"
  ],
  "Translation": "Matthias the Painter",
  "Librettist": "Hindemith",
  "Language": "German",
  "Based on": "Matthias Grünewald",
  "Premiere": "28 May 1938\nZurich Opera"
}